sunit
