Metadata-Version: 1.0
Name: nose-subunit
Version: 0.1.2
Summary: Subunit output adapter for nose
Home-page: http://www.liucougar.net/blog/nose-subunit
Author: liucougar
Author-email: liucougar@gmail.com
License: BSD
Download-URL: http://pypi.python.org/pypi/nose-subunit/
Keywords: test unittest nosetests nose plugin
Platform: Independent
Classifier: Development Status :: 3 - Alpha
Classifier: Environment :: Console
Classifier: Intended Audience :: Developers
Classifier: License :: OSI Approved :: Python Software Foundation License
Classifier: Operating System :: OS Independent
Classifier: Programming Language :: Python
Classifier: Topic :: Software Development :: Testing
